climux/__init__.py
climux/args.py
climux/cli.py
climux/command.py
climux/conftest.py
climux/convert.py
climux/py.typed
climux/test_climux.py
climux/utils.py
tests/__init__.py
tests/conftest.py
tests/test_args.py
tests/test_climux.py
tests/test_convert.py
tests/test_utils.py
climux-0.1.1.dist-info/LICENSE
climux-0.1.1.dist-info/METADATA
climux-0.1.1.dist-info/WHEEL
climux-0.1.1.dist-info/top_level.txt
climux-0.1.1.dist-info/RECORD
