Metadata-Version: 2.1
Name: climux
Version: 0.1.1
Summary: Library for writing command-line interfaces
Home-page: https://github.com/lggruspe/climux
Author: Levi Gruspe
Author-email: mail.levig@gmail.com
License: UNKNOWN
Platform: UNKNOWN
Classifier: Programming Language :: Python :: 3
Classifier: Programming Language :: Python :: 3.7
Classifier: Programming Language :: Python :: 3.8
Classifier: Programming Language :: Python :: 3.9
Classifier: License :: OSI Approved :: MIT License
Classifier: Environment :: Console
Requires-Python: >=3.7
Requires-Dist: infer-parser (==0.1.2)
